LICENSE
README.rst
setup.py
rickshaw/__init__.py
rickshaw/__main__.py
rickshaw/blue_waters.py
rickshaw/dbtools.py
rickshaw/deploy.py
rickshaw/docker_scheduler.py
rickshaw/generate.py
rickshaw/lazyasd.py
rickshaw/main.py
rickshaw/scheduler.py
rickshaw/server.py
rickshaw/server_scheduler.py
rickshaw/simspec.py
rickshaw/special_archs.py
rickshaw.egg-info/PKG-INFO
rickshaw.egg-info/SOURCES.txt
rickshaw.egg-info/dependency_links.txt
rickshaw.egg-info/not-zip-safe
rickshaw.egg-info/requires.txt
rickshaw.egg-info/top_level.txt
scripts/rickserv
scripts/rickshaw