Metadata-Version: 1.1
Name: rickshaw
Version: 1.5.3
Summary: Rickshaw is an automated driver for Cyclus
Home-page: https://github.com/ergs/rickshaw
Author: The ERGS developers
Author-email: ergsonomic@googlegroups.com
License: BSD 3-clause
Download-URL: https://github.com/ergs/rickshaw/zipball/1.5.3
Platform: UNKNOWN
Classifier: License :: OSI Approved
Classifier: Intended Audience :: Developers
Classifier: Programming Language :: Python
Classifier: Topic :: Utilities
